streamlit_octostar_research/__init__.py
streamlit_octostar_research/configure.py
streamlit_octostar_research/os_contextmenu.py
streamlit_octostar_research/os_dropzone.py
streamlit_octostar_research/os_searchbutton.py
streamlit_octostar_research/support.py
streamlit_octostar_research/desktop/__init__.py
streamlit_octostar_research/extras/__init__.py
streamlit_octostar_research/frontend/index.html
streamlit_octostar_research/frontend/main.js
streamlit_octostar_research/frontend/octostar-research-client.js
streamlit_octostar_research/frontend/octostar-research.js
streamlit_octostar_research/frontend/streamlit-component-lib.js
streamlit_octostar_research/ontology/__init__.py
streamlit_octostar_research-0.1.23.dist-info/LICENSE
streamlit_octostar_research-0.1.23.dist-info/METADATA
streamlit_octostar_research-0.1.23.dist-info/WHEEL
streamlit_octostar_research-0.1.23.dist-info/top_level.txt
streamlit_octostar_research-0.1.23.dist-info/RECORD
