Metadata-Version: 2.1
Name: streamlit-octostar-research
Version: 0.1.23
Summary: Streamlit component that connects to the Octostar Research App
Author: Octostar Research
Author-email: developer@octostarresearch.com
Requires-Python: >=3.7
License-File: LICENSE
Requires-Dist: streamlit >=1.2
Requires-Dist: jinja2
